Metadata-Version: 2.1
Name: redis-simple-cache-3k
Version: 0.0.7
Summary: redis-simple-cache is a pythonic interface for creating a cache over redis. It provides simple decorators that can be added to any function to cache its return values. 
Home-page: https://github.com/ohanetz/redis-simple-cache-3k
Author: Vivek Narayanan, Flávio Juvenal, Sam Zaydel. Python 3 and Redis 4 support by Omer Hanetz
Author-email: flaviojuvenal@gmail.com
License: 3-clause BSD
Keywords: decorator decorators redis cache
Platform: UNKNOWN
Classifier: Development Status :: 3 - Alpha
Classifier: Topic :: Utilities
Classifier: License :: OSI Approved :: BSD License
License-File: LICENSE
Requires-Dist: redis (>=4.0.0)
